{
  "pageIndex": 175,
  "lines": [
    {
      "sortKey": 1000,
      "text": "قُل لَّاۤ أَمۡلِكُ لِنَفۡسِی نَفۡعࣰا وَلَا ضَرًّا إِلَّا مَا شَاۤءَ ٱللَّهُۚ وَلَوۡ كُنتُ",
      "surahIndexFirst": 7,
      "ayahIndexFirst": 188,
      "isBasmala": false,
      "isTitle": false
    },
    {
      "sortKey": 2000,
      "text": "أَعۡلَمُ ٱلۡغَیۡبَ لَٱسۡتَكۡثَرۡتُ مِنَ ٱلۡخَیۡرِ وَمَا مَسَّنِیَ ٱلسُّوۤءُۚ",
      "surahIndexFirst": 7,
      "ayahIndexFirst": 188,
      "isBasmala": false,
      "isTitle": false
    },
    {
      "sortKey": 3000,
      "text": "إِنۡ أَنَا۠ إِلَّا نَذِیرࣱ وَبَشِیرࣱ لِّقَوۡمࣲ یُؤۡمِنُونَ ۝١٨٨ هُوَ ٱلَّذِی خَلَقَكُم",
      "surahIndexFirst": 7,
      "ayahIndexFirst": 188,
      "isBasmala": false,
      "isTitle": false
    },
    {
      "sortKey": 4000,
      "text": "مِّن نَّفۡسࣲ وَ ٰ⁠حِدَةࣲ وَجَعَلَ مِنۡهَا زَوۡجَهَا لِیَسۡكُنَ إِلَیۡهَاۖ فَلَمَّا",
      "surahIndexFirst": 7,
      "ayahIndexFirst": 189,
      "isBasmala": false,
      "isTitle": false,
      "semantic": [
        {
          "tokens": "تَغَشَّىٰهَا",
          "content": "واقعها",
          "tokenFromIndex": 13,
          "tokenToIndex": 13,
          "surahIndex": 7,
          "ayahIndex": 189
        },
        {
          "tokens": "فَمَرَّتْ بِهِۦ",
          "content": "فاستمرّت به بغير مشقّة",
          "tokenFromIndex": 17,
          "tokenToIndex": 18,
          "surahIndex": 7,
          "ayahIndex": 189
        },
        {
          "tokens": "أَثْقَلَت",
          "content": "صارت ذات ثِقل بكِبر الحمل",
          "tokenFromIndex": 20,
          "tokenToIndex": 20,
          "surahIndex": 7,
          "ayahIndex": 189
        },
        {
          "tokens": "صَٰلِحًا",
          "content": "نسلا سويّا أو ولدا سليما مثلنا",
          "tokenFromIndex": 26,
          "tokenToIndex": 26,
          "surahIndex": 7,
          "ayahIndex": 189
        }
      ]
    },
    {
      "sortKey": 5000,
      "text": "تَغَشَّىٰهَا حَمَلَتۡ حَمۡلًا خَفِیفࣰا فَمَرَّتۡ بِهِۦۖ فَلَمَّاۤ أَثۡقَلَت دَّعَوَا",
      "surahIndexFirst": 7,
      "ayahIndexFirst": 189,
      "isBasmala": false,
      "isTitle": false,
      "semantic": [
        {
          "tokens": "تَغَشَّىٰهَا",
          "content": "واقعها",
          "tokenFromIndex": 13,
          "tokenToIndex": 13,
          "surahIndex": 7,
          "ayahIndex": 189
        },
        {
          "tokens": "فَمَرَّتْ بِهِۦ",
          "content": "فاستمرّت به بغير مشقّة",
          "tokenFromIndex": 17,
          "tokenToIndex": 18,
          "surahIndex": 7,
          "ayahIndex": 189
        },
        {
          "tokens": "أَثْقَلَت",
          "content": "صارت ذات ثِقل بكِبر الحمل",
          "tokenFromIndex": 20,
          "tokenToIndex": 20,
          "surahIndex": 7,
          "ayahIndex": 189
        },
        {
          "tokens": "صَٰلِحًا",
          "content": "نسلا سويّا أو ولدا سليما مثلنا",
          "tokenFromIndex": 26,
          "tokenToIndex": 26,
          "surahIndex": 7,
          "ayahIndex": 189
        }
      ],
      "semanticSpans": [
        {
          "start": 0,
          "length": 12,
          "tokens": "تَغَشَّىٰهَا",
          "content": "واقعها"
        },
        {
          "start": 39,
          "length": 16,
          "tokens": "فَمَرَّتْ بِهِۦ",
          "content": "فاستمرّت به بغير مشقّة"
        },
        {
          "start": 66,
          "length": 9,
          "tokens": "أَثْقَلَت",
          "content": "صارت ذات ثِقل بكِبر الحمل"
        }
      ]
    },
    {
      "sortKey": 6000,
      "text": "ٱللَّهَ رَبَّهُمَا لَىِٕنۡ ءَاتَیۡتَنَا صَـٰلِحࣰا لَّنَكُونَنَّ مِنَ ٱلشَّـٰكِرِینَ ۝١٨٩",
      "surahIndexFirst": 7,
      "ayahIndexFirst": 189,
      "isBasmala": false,
      "isTitle": false,
      "semantic": [
        {
          "tokens": "تَغَشَّىٰهَا",
          "content": "واقعها",
          "tokenFromIndex": 13,
          "tokenToIndex": 13,
          "surahIndex": 7,
          "ayahIndex": 189
        },
        {
          "tokens": "فَمَرَّتْ بِهِۦ",
          "content": "فاستمرّت به بغير مشقّة",
          "tokenFromIndex": 17,
          "tokenToIndex": 18,
          "surahIndex": 7,
          "ayahIndex": 189
        },
        {
          "tokens": "أَثْقَلَت",
          "content": "صارت ذات ثِقل بكِبر الحمل",
          "tokenFromIndex": 20,
          "tokenToIndex": 20,
          "surahIndex": 7,
          "ayahIndex": 189
        },
        {
          "tokens": "صَٰلِحًا",
          "content": "نسلا سويّا أو ولدا سليما مثلنا",
          "tokenFromIndex": 26,
          "tokenToIndex": 26,
          "surahIndex": 7,
          "ayahIndex": 189
        }
      ],
      "semanticSpans": [
        {
          "start": 40,
          "length": 9,
          "tokens": "صَٰلِحًا",
          "content": "نسلا سويّا أو ولدا سليما مثلنا"
        }
      ]
    },
    {
      "sortKey": 7000,
      "text": "فَلَمَّاۤ ءَاتَىٰهُمَا صَـٰلِحࣰا جَعَلَا لَهُۥ شُرَكَاۤءَ فِیمَاۤ ءَاتَىٰهُمَاۚ فَتَعَـٰلَى",
      "surahIndexFirst": 7,
      "ayahIndexFirst": 190,
      "isBasmala": false,
      "isTitle": false,
      "semantic": [
        {
          "tokens": "جَعَلَا لَهُۥ شُرَكَآءَ",
          "content": "بتسمية ولديهما عبد الحارث بوسوسة ابليس مريدا بالحارث نفسه",
          "tokenFromIndex": 4,
          "tokenToIndex": 6,
          "surahIndex": 7,
          "ayahIndex": 190
        },
        {
          "tokens": "عَمَّا يُشْرِكُونَ",
          "content": "أي العرب بعبادة الأصنام",
          "tokenFromIndex": 11,
          "tokenToIndex": 12,
          "surahIndex": 7,
          "ayahIndex": 190
        }
      ],
      "semanticSpans": [
        {
          "start": 33,
          "length": 24,
          "tokens": "جَعَلَا لَهُۥ شُرَكَآءَ",
          "content": "بتسمية ولديهما عبد الحارث بوسوسة ابليس مريدا بالحارث نفسه"
        }
      ]
    },
    {
      "sortKey": 8000,
      "text": "ٱللَّهُ عَمَّا یُشۡرِكُونَ ۝١٩٠ أَیُشۡرِكُونَ مَا لَا یَخۡلُقُ شَیۡـࣰٔا وَهُمۡ یُخۡلَقُونَ ۝١٩١",
      "surahIndexFirst": 7,
      "ayahIndexFirst": 190,
      "isBasmala": false,
      "isTitle": false,
      "semantic": [
        {
          "tokens": "جَعَلَا لَهُۥ شُرَكَآءَ",
          "content": "بتسمية ولديهما عبد الحارث بوسوسة ابليس مريدا بالحارث نفسه",
          "tokenFromIndex": 4,
          "tokenToIndex": 6,
          "surahIndex": 7,
          "ayahIndex": 190
        },
        {
          "tokens": "عَمَّا يُشْرِكُونَ",
          "content": "أي العرب بعبادة الأصنام",
          "tokenFromIndex": 11,
          "tokenToIndex": 12,
          "surahIndex": 7,
          "ayahIndex": 190
        }
      ],
      "semanticSpans": [
        {
          "start": 8,
          "length": 18,
          "tokens": "عَمَّا يُشْرِكُونَ",
          "content": "أي العرب بعبادة الأصنام"
        }
      ]
    },
    {
      "sortKey": 9000,
      "text": "وَلَا یَسۡتَطِیعُونَ لَهُمۡ نَصۡرࣰا وَلَاۤ أَنفُسَهُمۡ یَنصُرُونَ ۝١٩٢",
      "surahIndexFirst": 7,
      "ayahIndexFirst": 192,
      "isBasmala": false,
      "isTitle": false
    },
    {
      "sortKey": 10000,
      "text": "وَإِن تَدۡعُوهُمۡ إِلَى ٱلۡهُدَىٰ لَا یَتَّبِعُوكُمۡۚ سَوَاۤءٌ عَلَیۡكُمۡ أَدَعَوۡتُمُوهُمۡ",
      "surahIndexFirst": 7,
      "ayahIndexFirst": 193,
      "isBasmala": false,
      "isTitle": false
    },
    {
      "sortKey": 11000,
      "text": "أَمۡ أَنتُمۡ صَـٰمِتُونَ ۝١٩٣ إِنَّ ٱلَّذِینَ تَدۡعُونَ مِن دُونِ ٱللَّهِ عِبَادٌ",
      "surahIndexFirst": 7,
      "ayahIndexFirst": 193,
      "isBasmala": false,
      "isTitle": false
    },
    {
      "sortKey": 12000,
      "text": "أَمۡثَالُكُمۡۖ فَٱدۡعُوهُمۡ فَلۡیَسۡتَجِیبُوا۟ لَكُمۡ إِن كُنتُمۡ",
      "surahIndexFirst": 7,
      "ayahIndexFirst": 194,
      "isBasmala": false,
      "isTitle": false
    },
    {
      "sortKey": 13000,
      "text": "صَـٰدِقِینَ ۝١٩٤ أَلَهُمۡ أَرۡجُلࣱ یَمۡشُونَ بِهَاۤۖ أَمۡ لَهُمۡ أَیۡدࣲ یَبۡطِشُونَ",
      "surahIndexFirst": 7,
      "ayahIndexFirst": 194,
      "isBasmala": false,
      "isTitle": false
    },
    {
      "sortKey": 14000,
      "text": "بِهَاۤۖ أَمۡ لَهُمۡ أَعۡیُنࣱ یُبۡصِرُونَ بِهَاۤۖ أَمۡ لَهُمۡ ءَاذَانࣱ یَسۡمَعُونَ",
      "surahIndexFirst": 7,
      "ayahIndexFirst": 195,
      "isBasmala": false,
      "isTitle": false,
      "semantic": [
        {
          "tokens": "فَلَا تُنظِرُونِ",
          "content": "فلا تُمهلوني ساعة",
          "tokenFromIndex": 25,
          "tokenToIndex": 26,
          "surahIndex": 7,
          "ayahIndex": 195
        }
      ]
    },
    {
      "sortKey": 15000,
      "text": "بِهَاۗ قُلِ ٱدۡعُوا۟ شُرَكَاۤءَكُمۡ ثُمَّ كِیدُونِ فَلَا تُنظِرُونِ ۝١٩٥",
      "surahIndexFirst": 7,
      "ayahIndexFirst": 195,
      "isBasmala": false,
      "isTitle": false,
      "semantic": [
        {
          "tokens": "فَلَا تُنظِرُونِ",
          "content": "فلا تُمهلوني ساعة",
          "tokenFromIndex": 25,
          "tokenToIndex": 26,
          "surahIndex": 7,
          "ayahIndex": 195
        }
      ],
      "semanticSpans": [
        {
          "start": 51,
          "length": 16,
          "tokens": "فَلَا تُنظِرُونِ",
          "content": "فلا تُمهلوني ساعة"
        }
      ]
    }
  ]
}